{
  "defType": "BiomeDef",
  "defName": "Desert",
  "label": "沙漠",
  "description": "非常干旱的地区，动植物数量稀少。沙漠要么很热要么很冷。",
  "animalDensity": 0.25,
  "plantDensity": 0.05,
  "diseaseMtbDays": 80.0,
  "hasVirtualPlants": true,
  "animalWeights": {
    "瞪羚": 0.0117647061,
    "鬣蜥": 0.7,
    "单峰骆驼": 0.25,
    "美洲狮": 0.02,
    "鸸鹋": 0.02,
    "鸵鸟": 0.2,
    "巨型甲虫": 1.0,
    "老鼠": 0.3,
    "爆炸羊": 0.0444444455,
    "耳廓狐": 0.02
  },
  "plantWeights": {
    "龙舌兰": 0.25,
    "巨掌仙人掌": 1.0,
    "针垫掌": 1.0,
    "灌木": 0.25,
    "草": 6.0,
    "蒲公英": 0.5,
    "杨树": 0.45
  },
  "diseaseWeights": {
    "流感": 100.0,
    "瘟疫": 80.0,
    "纤维纳米机械感染": 30.0,
    "感官纳米机械感染": 30.0,
    "肠道蠕虫": 60.0,
    "肌肉寄生虫": 60.0
  },
  "texture": "Texture_world_biomes_desert.png"
}